{
  "rows": [
    {
      "eventId": 80050,
      "eventName": "DRAFT 31424 - MT - TAIEX Expert Mission on EU General Data Protection Regulation (GDPR) & the handling of data for verification and evaluatio",
      "euLegislation": "04 Free movement of capital [10.40] (Complete)",
      "city": " ",
      "startDate": 4102441200000,
      "startDateYear": 2100,
      "startDateMonth": 1,
      "endDate": 4102441200000,
      "createDate": 1595887200000,
      "ofSigned": false,
      "erSigned": " ",
      "beneficiary": "Malta",
      "eventKeyword": "Crossborder payments,COVID 19",
      "beneficiaryInstitution": "Planning and Priorities Coordination Division (Managing Authority)",
      "eventType": "REGIO IND/EXP",
      "afSigned": false,
      "ibuCasehandler": " ",
      "ibuCasehandlerEmail": null,
      "ibuCasehandlerPhone": null,
      "teamLeader": "Helen LARSSON",
      "teamLeaderEmail": "Helen.LARSSON@ec.europa.eu",
      "teamLeaderPhone": "+32 2 29 91978",
      "coCasehandler": " ",
      "coCasehandlerEmail": null,
      "coCasehandlerPhone": null,
      "countryEventPlace": "Poland",
      "team": "INT MARKT",
      "eventCategory": "Expert Mission",
      "budgetGroup": "REGIO",
      "taskNo": 31424,
      "eventGroup": "TAIEX standard",
      "afSignDate": null,
      "ofSignDate": null,
      "seriesOfEvent": null,
      "accountCaseHandler": " ",
      "accountCaseHandlerEmail": null,
      "accountCaseHandlerPhone": null,
      "ticketCoCaseHandler": " ",
      "ticketCoCaseHandlerEmail": null,
      "ticketCoCaseHandlerPhone": null,
      "afStatus": " ",
      "ofStatus": " ",
      "invoicePeriod": null,
      "motherEventId": 80050,
      "eventAddCorr": 0,
      "eventRemark": null,
      "eventStatusReport": null,
      "ofSubmissionDate": null,
      "project": "REGIO PEER 2 PEER",
      "lastWorkflowStep": "Draft Event",
      "taiexContractor": "TAIEX - 8",
      "externalRequestId": null
    },
    {
      "eventId": 80049,
      "eventName": "DRAFT 30881 - PL - TAIEX Workshop green criteria in public p",
      "euLegislation": "TO BE DEFINED",
      "city": " ",
      "startDate": 4102441200000,
      "startDateYear": 2100,
      "startDateMonth": 1,
      "endDate": 4102441200000,
      "createDate": 1595887200000,
      "ofSigned": false,
      "erSigned": " ",
      "beneficiary": "Poland",
      "eventKeyword": "TO BE DEFINED",
      "beneficiaryInstitution": " Public Procurement Office of Poland",
      "eventType": "EIR",
      "afSigned": false,
      "ibuCasehandler": " ",
      "ibuCasehandlerEmail": null,
      "ibuCasehandlerPhone": null,
      "teamLeader": "Scott BOWEN",
      "teamLeaderEmail": "Scott.BOWEN@ec.europa.eu",
      "teamLeaderPhone": "+32 229-56519",
      "coCasehandler": " ",
      "coCasehandlerEmail": null,
      "coCasehandlerPhone": null,
      "countryEventPlace": "The Netherlands",
      "team": "ETT",
      "eventCategory": "Workshop",
      "budgetGroup": "EIR",
      "taskNo": 30881,
      "eventGroup": "TAIEX standard",
      "afSignDate": null,
      "ofSignDate": null,
      "seriesOfEvent": null,
      "accountCaseHandler": " ",
      "accountCaseHandlerEmail": null,
      "accountCaseHandlerPhone": null,
      "ticketCoCaseHandler": " ",
      "ticketCoCaseHandlerEmail": null,
      "ticketCoCaseHandlerPhone": null,
      "afStatus": " ",
      "ofStatus": " ",
      "invoicePeriod": null,
      "motherEventId": 80049,
      "eventAddCorr": 0,
      "eventRemark": null,
      "eventStatusReport": null,
      "ofSubmissionDate": null,
      "project": "EIR PEER 2 PEER",
      "lastWorkflowStep": "Draft Event",
      "taiexContractor": "TAIEX - 8",
      "externalRequestId": null
    },
    {
      "eventId": 80048,
      "eventName": "DRAFT 31413 - MD - TAIEX Expert Mission on Expert Mission on reviewing and providing an analysis of educational programs for high school students developed within the local school curriculum concerning organ/tissue/cell donation and transpl",
      "euLegislation": "26 Education and culture (Complete),28 Consumer and health protection (Partial),28.30 Health protection [15.30] (Complete)",
      "city": " ",
      "startDate": 1609455600000,
      "startDateYear": 2021,
      "startDateMonth": 1,
      "endDate": 1609455600000,
      "createDate": 1594936800000,
      "ofSigned": false,
      "erSigned": " ",
      "beneficiary": "Moldova",
      "eventKeyword": "Blood, tissues, cells and organs",
      "beneficiaryInstitution": "Ministry of Health, Transplant Agency; Ministry of Education, Culture and Research",
      "eventType": "AGR IND/EXP",
      "afSigned": false,
      "ibuCasehandler": "Mamatha ANANTHAPADMANABHACHAR",
      "ibuCasehandlerEmail": "Mamatha.ANANTHAPADMANABHACHAR@ext.ec.europa.eu",
      "ibuCasehandlerPhone": "56009",
      "teamLeader": "Tatjana BORBAS",
      "teamLeaderEmail": "Tatjana.BORBAS@ec.europa.eu",
      "teamLeaderPhone": "+32 2 29 58951",
      "coCasehandler": " ",
      "coCasehandlerEmail": null,
      "coCasehandlerPhone": null,
      "countryEventPlace": "The Netherlands",
      "team": "AGR",
      "eventCategory": "Expert Mission",
      "budgetGroup": "ENPI EAST",
      "taskNo": 31413,
      "eventGroup": "TAIEX standard",
      "afSignDate": null,
      "ofSignDate": null,
      "seriesOfEvent": null,
      "accountCaseHandler": " ",
      "accountCaseHandlerEmail": null,
      "accountCaseHandlerPhone": null,
      "ticketCoCaseHandler": " ",
      "ticketCoCaseHandlerEmail": null,
      "ticketCoCaseHandlerPhone": null,
      "afStatus": " ",
      "ofStatus": " ",
      "invoicePeriod": null,
      "motherEventId": 80048,
      "eventAddCorr": 0,
      "eventRemark": null,
      "eventStatusReport": null,
      "ofSubmissionDate": null,
      "project": "IPA, ENI",
      "lastWorkflowStep": "AF Finished",
      "taiexContractor": "TAIEX - 8",
      "externalRequestId": null
    },
    {
      "eventId": 80047,
      "eventName": "TO BE DEFINED",
      "euLegislation": "23 Judiciary and fundamental rights [20] (Complete)",
      "city": "Brussels",
      "startDate": 4102441200000,
      "startDateYear": 2100,
      "startDateMonth": 1,
      "endDate": 4102441200000,
      "createDate": 1594936800000,
      "ofSigned": false,
      "erSigned": " ",
      "beneficiary": "TO BE DEFINED",
      "eventKeyword": "Human rights,Gender equality,Chapter 23,Women's rights,Deliverable - Good Governance,WBS - Flagship 1",
      "beneficiaryInstitution": "All NEAR Partners",
      "eventType": "JHA",
      "afSigned": false,
      "ibuCasehandler": "Werner STAPPAERTS",
      "ibuCasehandlerEmail": "Werner.STAPPAERTS@ext.ec.europa.eu",
      "ibuCasehandlerPhone": "+32 229-96894",
      "teamLeader": "Jovita GUDELYTE",
      "teamLeaderEmail": "Jovita.GUDELYTE@ec.europa.eu",
      "teamLeaderPhone": "+32 2 29 54785",
      "coCasehandler": " ",
      "coCasehandlerEmail": null,
      "coCasehandlerPhone": null,
      "countryEventPlace": "Belgium",
      "team": "JHA",
      "eventCategory": "Workshop",
      "budgetGroup": "TO BE DEFINED",
      "taskNo": 31420,
      "eventGroup": "TAIEX strategic",
      "afSignDate": 1591785494000,
      "ofSignDate": null,
      "seriesOfEvent": null,
      "accountCaseHandler": " ",
      "accountCaseHandlerEmail": null,
      "accountCaseHandlerPhone": null,
      "ticketCoCaseHandler": " ",
      "ticketCoCaseHandlerEmail": null,
      "ticketCoCaseHandlerPhone": null,
      "afStatus": " ",
      "ofStatus": " ",
      "invoicePeriod": null,
      "motherEventId": 80047,
      "eventAddCorr": 0,
      "eventRemark": null,
      "eventStatusReport": null,
      "ofSubmissionDate": null,
      "project": "IPA, ENI",
      "lastWorkflowStep": "Draft Event",
      "taiexContractor": "TAIEX - 8",
      "externalRequestId": null
    },
    {
      "eventId": 80046,
      "eventName": "DRAFT 31430 - AL - TAIEX Expert Mission o",
      "euLegislation": "10 Information society and media (Complete),04 Free movement of capital [10.40] (Complete)",
      "city": " Stidia ",
      "startDate": 4102441200000,
      "startDateYear": 2100,
      "startDateMonth": 1,
      "endDate": 4102441200000,
      "createDate": 1594764000000,
      "ofSigned": false,
      "erSigned": " ",
      "beneficiary": "Albania",
      "eventKeyword": "Crossborder payments",
      "beneficiaryInstitution": "sdf",
      "eventType": "ETT",
      "afSigned": false,
      "ibuCasehandler": " ",
      "ibuCasehandlerEmail": null,
      "ibuCasehandlerPhone": null,
      "teamLeader": "Scott BOWEN",
      "teamLeaderEmail": "Scott.BOWEN@ec.europa.eu",
      "teamLeaderPhone": "+32 229-56519",
      "coCasehandler": " ",
      "coCasehandlerEmail": null,
      "coCasehandlerPhone": null,
      "countryEventPlace": "Algeria",
      "team": "ETT",
      "eventCategory": "Workshop",
      "budgetGroup": "IPA",
      "taskNo": 31430,
      "eventGroup": "TAIEX standard",
      "afSignDate": null,
      "ofSignDate": null,
      "seriesOfEvent": null,
      "accountCaseHandler": " ",
      "accountCaseHandlerEmail": null,
      "accountCaseHandlerPhone": null,
      "ticketCoCaseHandler": " ",
      "ticketCoCaseHandlerEmail": null,
      "ticketCoCaseHandlerPhone": null,
      "afStatus": " ",
      "ofStatus": " ",
      "invoicePeriod": null,
      "motherEventId": 80046,
      "eventAddCorr": 0,
      "eventRemark": null,
      "eventStatusReport": null,
      "ofSubmissionDate": null,
      "project": "IPA, ENI",
      "lastWorkflowStep": "Draft Event",
      "taiexContractor": "TAIEX - 8",
      "externalRequestId": null
    },
    {
      "eventId": 80045,
      "eventName": "Proc event - testing TAIEX-8",
      "euLegislation": "TAIEX procurements (Complete)",
      "city": "Brussels",
      "startDate": 1596405600000,
      "startDateYear": 2020,
      "startDateMonth": 8,
      "endDate": 1598824800000,
      "createDate": 1594677600000,
      "ofSigned": true,
      "erSigned": " ",
      "beneficiary": "TO BE DEFINED",
      "eventKeyword": "Other cost",
      "beneficiaryInstitution": null,
      "eventType": "PROC",
      "afSigned": true,
      "ibuCasehandler": "Tania ANGUELOVA",
      "ibuCasehandlerEmail": "Tania.ANGUELOVA@ec.europa.eu",
      "ibuCasehandlerPhone": "56360",
      "teamLeader": "Peter POLAJNAR",
      "teamLeaderEmail": "Peter.POLAJNAR@ec.europa.eu",
      "teamLeaderPhone": "+32 2 29 80146",
      "coCasehandler": "TAIEX_8 CCH_LM",
      "coCasehandlerEmail": "taiex_8_cch@taiex.be",
      "coCasehandlerPhone": null,
      "countryEventPlace": "TAIEX Office",
      "team": "PROC",
      "eventCategory": "Procurement",
      "budgetGroup": "TO BE DEFINED",
      "taskNo": null,
      "eventGroup": "Other",
      "afSignDate": 1594729679000,
      "ofSignDate": 1594730039000,
      "seriesOfEvent": null,
      "accountCaseHandler": "Werner Stappaerts",
      "accountCaseHandlerEmail": "werner.stappaerts@live.be",
      "accountCaseHandlerPhone": "89089",
      "ticketCoCaseHandler": " ",
      "ticketCoCaseHandlerEmail": null,
      "ticketCoCaseHandlerPhone": null,
      "afStatus": "Y",
      "ofStatus": "Y",
      "invoicePeriod": "Q1/TAIEX_2020",
      "motherEventId": 80045,
      "eventAddCorr": 0,
      "eventRemark": null,
      "eventStatusReport": null,
      "ofSubmissionDate": null,
      "project": "IPA, ENI",
      "lastWorkflowStep": "TL Checklist Approved",
      "taiexContractor": "TAIEX - 8",
      "externalRequestId": null
    },
    {
      "eventId": 80044,
      "eventName": "Add. 1 to 2007/80043 - TAIEX EPPA Regional Workshop on reducing the emissions of certain atmospheric ",
      "euLegislation": "27 Environment [15] (Partial),27.10 Environment [15.10] (Partial),27.10.20 Pollution and nuisances [15.10.20] (Partial),27.10.20.30 Monitoring of atmospheric pollution [15.10.20.30] (Complete)",
      "city": "Vienna",
      "startDate": 1603058400000,
      "startDateYear": 2020,
      "startDateMonth": 10,
      "endDate": 1603144800000,
      "createDate": 1594677600000,
      "ofSigned": true,
      "erSigned": " ",
      "beneficiary": "Albania,Montenegro,North Macedonia,Serbia,Bosnia and Herzegovina,Kosovo",
      "eventKeyword": "Air,Chapter 27",
      "beneficiaryInstitution": null,
      "eventType": "EPPA",
      "afSigned": true,
      "ibuCasehandler": "Nicolas  MENDOZA",
      "ibuCasehandlerEmail": "Jose.DOMINGUEZ-MENDOZA1@ec.europa.eu",
      "ibuCasehandlerPhone": "80990",
      "teamLeader": "Scott BOWEN",
      "teamLeaderEmail": "Scott.BOWEN@ec.europa.eu",
      "teamLeaderPhone": "+32 229-56519",
      "coCasehandler": "TAIEX_8 CCH_LM",
      "coCasehandlerEmail": "taiex_8_cch@taiex.be",
      "coCasehandlerPhone": null,
      "countryEventPlace": "Austria",
      "team": "ETT",
      "eventCategory": "Workshop",
      "budgetGroup": "TO BE DEFINED",
      "taskNo": 31065,
      "eventGroup": null,
      "afSignDate": null,
      "ofSignDate": 1594718771000,
      "seriesOfEvent": null,
      "accountCaseHandler": "Werner Stappaerts",
      "accountCaseHandlerEmail": "werner.stappaerts@live.be",
      "accountCaseHandlerPhone": "89089",
      "ticketCoCaseHandler": " ",
      "ticketCoCaseHandlerEmail": null,
      "ticketCoCaseHandlerPhone": null,
      "afStatus": "Y",
      "ofStatus": "Y",
      "invoicePeriod": null,
      "motherEventId": 80043,
      "eventAddCorr": 2,
      "eventRemark": null,
      "eventStatusReport": null,
      "ofSubmissionDate": null,
      "project": "IPA, ENI",
      "lastWorkflowStep": "OF Signed",
      "taiexContractor": "TAIEX - 8",
      "externalRequestId": null
    },
    {
      "eventId": 80043,
      "eventName": "TAIEX EPPA Regional Workshop on reducing the emissions of certain atmospheric pollutants",
      "euLegislation": "27 Environment [15] (Partial),27.10 Environment [15.10] (Partial),27.10.20 Pollution and nuisances [15.10.20] (Partial),27.10.20.30 Monitoring of atmospheric pollution [15.10.20.30] (Complete)",
      "city": "Vienna",
      "startDate": 1603058400000,
      "startDateYear": 2020,
      "startDateMonth": 10,
      "endDate": 1603144800000,
      "createDate": 1594677600000,
      "ofSigned": true,
      "erSigned": " ",
      "beneficiary": "TO BE DEFINED",
      "eventKeyword": "Chapter 27,Air",
      "beneficiaryInstitution": "Line Ministries in EPPA Beneficiary Countries (responsible for environmental policies)",
      "eventType": "EPPA",
      "afSigned": true,
      "ibuCasehandler": "Nicolas  MENDOZA",
      "ibuCasehandlerEmail": "Jose.DOMINGUEZ-MENDOZA1@ec.europa.eu",
      "ibuCasehandlerPhone": "80990",
      "teamLeader": "Scott BOWEN",
      "teamLeaderEmail": "Scott.BOWEN@ec.europa.eu",
      "teamLeaderPhone": "+32 229-56519",
      "coCasehandler": "TAIEX_8 CCH_LM",
      "coCasehandlerEmail": "taiex_8_cch@taiex.be",
      "coCasehandlerPhone": null,
      "countryEventPlace": "Austria",
      "team": "ETT",
      "eventCategory": "Workshop",
      "budgetGroup": "TO BE DEFINED",
      "taskNo": 31065,
      "eventGroup": "TAIEX strategic",
      "afSignDate": 1594716743000,
      "ofSignDate": 1594717818000,
      "seriesOfEvent": null,
      "accountCaseHandler": "Werner Stappaerts",
      "accountCaseHandlerEmail": "werner.stappaerts@live.be",
      "accountCaseHandlerPhone": "89089",
      "ticketCoCaseHandler": " ",
      "ticketCoCaseHandlerEmail": null,
      "ticketCoCaseHandlerPhone": null,
      "afStatus": "Y",
      "ofStatus": "Y",
      "invoicePeriod": "Q1/TAIEX_2020",
      "motherEventId": 80043,
      "eventAddCorr": 1,
      "eventRemark": null,
      "eventStatusReport": null,
      "ofSubmissionDate": 1597269600000,
      "project": "IPA, ENI",
      "lastWorkflowStep": "OF Signed",
      "taiexContractor": "TAIEX - 8",
      "externalRequestId": null
    },
    {
      "eventId": 80042,
      "eventName": "DRAFT 31431 - QA - TAIEX Workshop on EU-Qatar: European cooperation network of employment services' sharing best practices in developing and administering a job-matchin",
      "euLegislation": "02.10 Freedom of movement for workers [05.10] (Complete),02 Freedom of movement for workers (Partial)",
      "city": " ",
      "startDate": 4102441200000,
      "startDateYear": 2100,
      "startDateMonth": 1,
      "endDate": 4102441200000,
      "createDate": 1594591200000,
      "ofSigned": false,
      "erSigned": " ",
      "beneficiary": "Qatar",
      "eventKeyword": "Migrant workers",
      "beneficiaryInstitution": "Ministry of Administrative Development Labour and Social Affairs (ADLSA) of the State of Qatar",
      "eventType": "PI",
      "afSigned": false,
      "ibuCasehandler": " ",
      "ibuCasehandlerEmail": null,
      "ibuCasehandlerPhone": null,
      "teamLeader": "Peter POLAJNAR",
      "teamLeaderEmail": "Peter.POLAJNAR@ec.europa.eu",
      "teamLeaderPhone": "+32 2 29 80146",
      "coCasehandler": " ",
      "coCasehandlerEmail": null,
      "coCasehandlerPhone": null,
      "countryEventPlace": "Belgium",
      "team": "HRZ",
      "eventCategory": "Workshop",
      "budgetGroup": "PI",
      "taskNo": 31431,
      "eventGroup": "TAIEX standard",
      "afSignDate": null,
      "ofSignDate": null,
      "seriesOfEvent": null,
      "accountCaseHandler": " ",
      "accountCaseHandlerEmail": null,
      "accountCaseHandlerPhone": null,
      "ticketCoCaseHandler": " ",
      "ticketCoCaseHandlerEmail": null,
      "ticketCoCaseHandlerPhone": null,
      "afStatus": " ",
      "ofStatus": " ",
      "invoicePeriod": null,
      "motherEventId": 80042,
      "eventAddCorr": 0,
      "eventRemark": null,
      "eventStatusReport": null,
      "ofSubmissionDate": null,
      "project": "PI",
      "lastWorkflowStep": "Draft Event",
      "taiexContractor": "TAIEX - 8",
      "externalRequestId": null
    },
    {
      "eventId": 80041,
      "eventName": "DRAFT 31432 - KS - TAIEX Expert Mission on ECAA Assessment visit",
      "euLegislation": "04 Free movement of capital [10.40] (Complete)",
      "city": "Ainaži",
      "startDate": 4102441200000,
      "startDateYear": 2100,
      "startDateMonth": 1,
      "endDate": 4102441200000,
      "createDate": 1594591200000,
      "ofSigned": false,
      "erSigned": " ",
      "beneficiary": "Kosovo",
      "eventKeyword": "Crossborder payments in euros,Deliverable - Connectivity",
      "beneficiaryInstitution": "Civil Aviation Authority of Kosovo",
      "eventType": "ETT IND/EXP",
      "afSigned": false,
      "ibuCasehandler": " ",
      "ibuCasehandlerEmail": null,
      "ibuCasehandlerPhone": null,
      "teamLeader": "Scott BOWEN",
      "teamLeaderEmail": "Scott.BOWEN@ec.europa.eu",
      "teamLeaderPhone": "+32 229-56519",
      "coCasehandler": " ",
      "coCasehandlerEmail": null,
      "coCasehandlerPhone": null,
      "countryEventPlace": "Latvia",
      "team": "ETT",
      "eventCategory": "Expert Mission",
      "budgetGroup": "IPA",
      "taskNo": 31432,
      "eventGroup": "TAIEX strategic",
      "afSignDate": null,
      "ofSignDate": null,
      "seriesOfEvent": null,
      "accountCaseHandler": " ",
      "accountCaseHandlerEmail": null,
      "accountCaseHandlerPhone": null,
      "ticketCoCaseHandler": " ",
      "ticketCoCaseHandlerEmail": null,
      "ticketCoCaseHandlerPhone": null,
      "afStatus": " ",
      "ofStatus": " ",
      "invoicePeriod": null,
      "motherEventId": 80041,
      "eventAddCorr": 0,
      "eventRemark": null,
      "eventStatusReport": null,
      "ofSubmissionDate": null,
      "project": "IPA, ENI",
      "lastWorkflowStep": "Draft Event",
      "taiexContractor": "TAIEX - 8",
      "externalRequestId": null
    },
    {
      "eventId": 80040,
      "eventName": "DRAFT 31428 - PS - TAIEX Expert Miss",
      "euLegislation": "04 Free movement of capital [10.40] (Complete)",
      "city": " ",
      "startDate": 4102441200000,
      "startDateYear": 2100,
      "startDateMonth": 1,
      "endDate": 4102441200000,
      "createDate": 1594591200000,
      "ofSigned": false,
      "erSigned": " ",
      "beneficiary": "Palestine",
      "eventKeyword": "COVID 19",
      "beneficiaryInstitution": "asdfasdf",
      "eventType": "AGR",
      "afSigned": false,
      "ibuCasehandler": " ",
      "ibuCasehandlerEmail": null,
      "ibuCasehandlerPhone": null,
      "teamLeader": "Scott BOWEN",
      "teamLeaderEmail": "Scott.BOWEN@ec.europa.eu",
      "teamLeaderPhone": "+32 229-56519",
      "coCasehandler": " ",
      "coCasehandlerEmail": null,
      "coCasehandlerPhone": null,
      "countryEventPlace": "Poland",
      "team": "AGR",
      "eventCategory": "Workshop",
      "budgetGroup": "ENPI SOUTH",
      "taskNo": 31428,
      "eventGroup": "TAIEX strategic",
      "afSignDate": null,
      "ofSignDate": null,
      "seriesOfEvent": null,
      "accountCaseHandler": " ",
      "accountCaseHandlerEmail": null,
      "accountCaseHandlerPhone": null,
      "ticketCoCaseHandler": " ",
      "ticketCoCaseHandlerEmail": null,
      "ticketCoCaseHandlerPhone": null,
      "afStatus": " ",
      "ofStatus": " ",
      "invoicePeriod": null,
      "motherEventId": 80040,
      "eventAddCorr": 0,
      "eventRemark": null,
      "eventStatusReport": null,
      "ofSubmissionDate": null,
      "project": "IPA, ENI",
      "lastWorkflowStep": "Draft Event",
      "taiexContractor": "TAIEX - 8",
      "externalRequestId": null
    },
    {
      "eventId": 80038,
      "eventName": "DRAFT 31305 - TC - TAIEX Expert Mission on ",
      "euLegislation": "12 Food safety, veterinary and phytosanitary policy (Partial),12.20 Foodstuffs [13.30.14] (Partial),12.20.30 Other provisions [13.30.14.30] (Complete),12.30 Protection of animals [15.40] (Complete)",
      "city": " ",
      "startDate": 4102441200000,
      "startDateYear": 2100,
      "startDateMonth": 1,
      "endDate": 4102441200000,
      "createDate": 1594591200000,
      "ofSigned": false,
      "erSigned": " ",
      "beneficiary": "Turkish Cypriot community",
      "eventKeyword": "Additives authorised and purity criteria",
      "beneficiaryInstitution": "Veterinary department",
      "eventType": "ATCC HOME",
      "afSigned": false,
      "ibuCasehandler": "Tania ANGUELOVA",
      "ibuCasehandlerEmail": "Tania.ANGUELOVA@ec.europa.eu",
      "ibuCasehandlerPhone": "56360",
      "teamLeader": "Scott BOWEN",
      "teamLeaderEmail": "Scott.BOWEN@ec.europa.eu",
      "teamLeaderPhone": "+32 229-56519",
      "coCasehandler": " ",
      "coCasehandlerEmail": null,
      "coCasehandlerPhone": null,
      "countryEventPlace": "TO BE DEFINED",
      "team": "TCC",
      "eventCategory": "Work from Home",
      "budgetGroup": "TCC",
      "taskNo": 31305,
      "eventGroup": "TAIEX standard",
      "afSignDate": null,
      "ofSignDate": null,
      "seriesOfEvent": null,
      "accountCaseHandler": " ",
      "accountCaseHandlerEmail": null,
      "accountCaseHandlerPhone": null,
      "ticketCoCaseHandler": " ",
      "ticketCoCaseHandlerEmail": null,
      "ticketCoCaseHandlerPhone": null,
      "afStatus": " ",
      "ofStatus": " ",
      "invoicePeriod": null,
      "motherEventId": 80038,
      "eventAddCorr": 0,
      "eventRemark": null,
      "eventStatusReport": null,
      "ofSubmissionDate": null,
      "project": "TCC",
      "lastWorkflowStep": "Draft Event",
      "taiexContractor": "TAIEX - 8",
      "externalRequestId": null
    },
    {
      "eventId": 80037,
      "eventName": "DRAFT 31403 - IL - TAIEX Expert Mission on Estonia's X-road and",
      "euLegislation": "10 Information society and media (Complete),18 Statistics (Complete)",
      "city": "Abel-beth-maachah",
      "startDate": 4102441200000,
      "startDateYear": 2100,
      "startDateMonth": 1,
      "endDate": 4102441200000,
      "createDate": 1594591200000,
      "ofSigned": false,
      "erSigned": " ",
      "beneficiary": "Israel",
      "eventKeyword": "Statistics users",
      "beneficiaryInstitution": "Central Bureau of Statistics",
      "eventType": "ETT IND/EXP",
      "afSigned": false,
      "ibuCasehandler": "Francesca AQUARO",
      "ibuCasehandlerEmail": "Francesca.AQUARO@ec.europa.eu",
      "ibuCasehandlerPhone": "+32 2 29 96132",
      "teamLeader": "Scott BOWEN",
      "teamLeaderEmail": "Scott.BOWEN@ec.europa.eu",
      "teamLeaderPhone": "+32 229-56519",
      "coCasehandler": " ",
      "coCasehandlerEmail": null,
      "coCasehandlerPhone": null,
      "countryEventPlace": "Israel",
      "team": "ETT",
      "eventCategory": "Expert Mission",
      "budgetGroup": "ENPI SOUTH",
      "taskNo": 31403,
      "eventGroup": "TAIEX standard",
      "afSignDate": null,
      "ofSignDate": null,
      "seriesOfEvent": null,
      "accountCaseHandler": " ",
      "accountCaseHandlerEmail": null,
      "accountCaseHandlerPhone": null,
      "ticketCoCaseHandler": " ",
      "ticketCoCaseHandlerEmail": null,
      "ticketCoCaseHandlerPhone": null,
      "afStatus": " ",
      "ofStatus": " ",
      "invoicePeriod": null,
      "motherEventId": 80037,
      "eventAddCorr": 0,
      "eventRemark": null,
      "eventStatusReport": null,
      "ofSubmissionDate": null,
      "project": "IPA, ENI",
      "lastWorkflowStep": "Draft Event",
      "taiexContractor": "TAIEX - 8",
      "externalRequestId": null
    },
    {
      "eventId": 80036,
      "eventName": "Expenditure ver. - test taiex 8",
      "euLegislation": "TAIEX procurements (Complete)",
      "city": "Brussels",
      "startDate": 1599429600000,
      "startDateYear": 2020,
      "startDateMonth": 9,
      "endDate": 1601416800000,
      "createDate": 1594591200000,
      "ofSigned": true,
      "erSigned": " ",
      "beneficiary": "TO BE DEFINED",
      "eventKeyword": "Report ",
      "beneficiaryInstitution": null,
      "eventType": "EXV",
      "afSigned": true,
      "ibuCasehandler": "Iva BABIC",
      "ibuCasehandlerEmail": "Iva.BABIC@ec.europa.eu",
      "ibuCasehandlerPhone": "+32 2 29 84944",
      "teamLeader": "Peter POLAJNAR",
      "teamLeaderEmail": "Peter.POLAJNAR@ec.europa.eu",
      "teamLeaderPhone": "+32 2 29 80146",
      "coCasehandler": "TAIEX_8 CCH_LM",
      "coCasehandlerEmail": "taiex_8_cch@taiex.be",
      "coCasehandlerPhone": null,
      "countryEventPlace": "TAIEX Office",
      "team": "PROC",
      "eventCategory": "Procurement",
      "budgetGroup": "TO BE DEFINED",
      "taskNo": null,
      "eventGroup": "TAIEX standard",
      "afSignDate": 1594623449000,
      "ofSignDate": 1594640910000,
      "seriesOfEvent": null,
      "accountCaseHandler": " ",
      "accountCaseHandlerEmail": null,
      "accountCaseHandlerPhone": null,
      "ticketCoCaseHandler": " ",
      "ticketCoCaseHandlerEmail": null,
      "ticketCoCaseHandlerPhone": null,
      "afStatus": "Y",
      "ofStatus": "Y",
      "invoicePeriod": null,
      "motherEventId": 80036,
      "eventAddCorr": 0,
      "eventRemark": null,
      "eventStatusReport": null,
      "ofSubmissionDate": null,
      "project": "IPA, ENI",
      "lastWorkflowStep": "TL Checklist Approved",
      "taiexContractor": "TAIEX - 8",
      "externalRequestId": null
    },
    {
      "eventId": 80035,
      "eventName": "New TAIEX-8 from scratch",
      "euLegislation": "04 Free movement of capital [10.40] (Complete)",
      "city": "Andrushivka",
      "startDate": 1599688800000,
      "startDateYear": 2020,
      "startDateMonth": 9,
      "endDate": 1599775200000,
      "createDate": 1594591200000,
      "ofSigned": false,
      "erSigned": " ",
      "beneficiary": "Ukraine",
      "eventKeyword": "Crossborder payments",
      "beneficiaryInstitution": null,
      "eventType": "AGR",
      "afSigned": true,
      "ibuCasehandler": "Tania ANGUELOVA",
      "ibuCasehandlerEmail": "Tania.ANGUELOVA@ec.europa.eu",
      "ibuCasehandlerPhone": "56360",
      "teamLeader": "Tatjana BORBAS",
      "teamLeaderEmail": "Tatjana.BORBAS@ec.europa.eu",
      "teamLeaderPhone": "+32 2 29 58951",
      "coCasehandler": " ",
      "coCasehandlerEmail": null,
      "coCasehandlerPhone": null,
      "countryEventPlace": "Ukraine",
      "team": "AGR",
      "eventCategory": "Workshop",
      "budgetGroup": "ENPI EAST",
      "taskNo": null,
      "eventGroup": "TAIEX standard",
      "afSignDate": 1594646633000,
      "ofSignDate": null,
      "seriesOfEvent": null,
      "accountCaseHandler": " ",
      "accountCaseHandlerEmail": null,
      "accountCaseHandlerPhone": null,
      "ticketCoCaseHandler": " ",
      "ticketCoCaseHandlerEmail": null,
      "ticketCoCaseHandlerPhone": null,
      "afStatus": "Y",
      "ofStatus": " ",
      "invoicePeriod": null,
      "motherEventId": 80035,
      "eventAddCorr": 0,
      "eventRemark": null,
      "eventStatusReport": null,
      "ofSubmissionDate": null,
      "project": "IPA, ENI",
      "lastWorkflowStep": "Logistics can Start",
      "taiexContractor": "TAIEX - 8",
      "externalRequestId": null
    },
    {
      "eventId": 80034,
      "eventName": "New event TAIEX 8 with speaker copy",
      "euLegislation": "24 Justice, freedom and security [19] (Complete)",
      "city": "Yerevan",
      "startDate": 1602712800000,
      "startDateYear": 2020,
      "startDateMonth": 10,
      "endDate": 1602799200000,
      "createDate": 1594591200000,
      "ofSigned": false,
      "erSigned": " ",
      "beneficiary": "Armenia",
      "eventKeyword": "Police cooperation,Deliverable - Good Governance",
      "beneficiaryInstitution": "DG NEAR",
      "eventType": "AGR IND/EXP",
      "afSigned": true,
      "ibuCasehandler": "Werner STAPPAERTS",
      "ibuCasehandlerEmail": "Werner.STAPPAERTS@ext.ec.europa.eu",
      "ibuCasehandlerPhone": "+32 229-96894",
      "teamLeader": "Jovita GUDELYTE",
      "teamLeaderEmail": "Jovita.GUDELYTE@ec.europa.eu",
      "teamLeaderPhone": "+32 2 29 54785",
      "coCasehandler": " ",
      "coCasehandlerEmail": null,
      "coCasehandlerPhone": null,
      "countryEventPlace": "Armenia",
      "team": "AGR",
      "eventCategory": "Expert Mission",
      "budgetGroup": "ENPI EAST",
      "taskNo": 30459,
      "eventGroup": "TAIEX strategic",
      "afSignDate": 1594621579000,
      "ofSignDate": null,
      "seriesOfEvent": null,
      "accountCaseHandler": " ",
      "accountCaseHandlerEmail": null,
      "accountCaseHandlerPhone": null,
      "ticketCoCaseHandler": " ",
      "ticketCoCaseHandlerEmail": null,
      "ticketCoCaseHandlerPhone": null,
      "afStatus": "Y",
      "ofStatus": " ",
      "invoicePeriod": null,
      "motherEventId": 80034,
      "eventAddCorr": 0,
      "eventRemark": null,
      "eventStatusReport": null,
      "ofSubmissionDate": null,
      "project": "IPA, ENI",
      "lastWorkflowStep": "Logistics can Start",
      "taiexContractor": "TAIEX - 8",
      "externalRequestId": null
    },
    {
      "eventId": 80033,
      "eventName": "DRAFT 31425 - LT - TAIEX Workshop on Green procurement 31425 - LT - TAIEX Workshop on Green procurement31425 - LT - TAIEX Workshop on Green procurement31425 - LT - TAIEX Workshop on Green procurement31425 - LT - TAIEX Workshop on Green procurement31425 - LT - TAIEX Workshop on Green procurement31425 - LT - TAIEX Workshop on Green procurement31425 - LT - TAIEX Workshop on Green procurement31425",
      "euLegislation": "04 Free movement of capital [10.40] (Complete)",
      "city": "Abbotsford, Johannesburg",
      "startDate": 4102441200000,
      "startDateYear": 2100,
      "startDateMonth": 1,
      "endDate": 4102441200000,
      "createDate": 1594591200000,
      "ofSigned": false,
      "erSigned": " ",
      "beneficiary": "Lithuania",
      "eventKeyword": "Crossborder payments",
      "beneficiaryInstitution": "Ministry of Environment of the Republic of Lithuania, Environmental Projects Management Agency",
      "eventType": "REGIO",
      "afSigned": false,
      "ibuCasehandler": "Mamatha ANANTHAPADMANABHACHAR",
      "ibuCasehandlerEmail": "Mamatha.ANANTHAPADMANABHACHAR@ext.ec.europa.eu",
      "ibuCasehandlerPhone": "56009",
      "teamLeader": "Helen LARSSON",
      "teamLeaderEmail": "Helen.LARSSON@ec.europa.eu",
      "teamLeaderPhone": "+32 2 29 91978",
      "coCasehandler": " ",
      "coCasehandlerEmail": null,
      "coCasehandlerPhone": null,
      "countryEventPlace": "South Africa",
      "team": "INT MARKT",
      "eventCategory": "Workshop",
      "budgetGroup": "REGIO",
      "taskNo": 31425,
      "eventGroup": "TAIEX strategic",
      "afSignDate": null,
      "ofSignDate": null,
      "seriesOfEvent": null,
      "accountCaseHandler": " ",
      "accountCaseHandlerEmail": null,
      "accountCaseHandlerPhone": null,
      "ticketCoCaseHandler": " ",
      "ticketCoCaseHandlerEmail": null,
      "ticketCoCaseHandlerPhone": null,
      "afStatus": " ",
      "ofStatus": " ",
      "invoicePeriod": null,
      "motherEventId": 80033,
      "eventAddCorr": 0,
      "eventRemark": null,
      "eventStatusReport": null,
      "ofSubmissionDate": null,
      "project": "REGIO PEER 2 PEER",
      "lastWorkflowStep": "Draft Event",
      "taiexContractor": "TAIEX - 8",
      "externalRequestId": null
    },
    {
      "eventId": 80032,
      "eventName": "Workshop on Agri-food exports and tertilisers",
      "euLegislation": "11 Agriculture and rural development [03] (Partial),11.80 Agreements with non-member countries [03.80] (Complete)",
      "city": "Lisbon",
      "startDate": 1600898400000,
      "startDateYear": 2020,
      "startDateMonth": 9,
      "endDate": 1600984800000,
      "createDate": 1594418400000,
      "ofSigned": false,
      "erSigned": " ",
      "beneficiary": "TO BE DEFINED",
      "eventKeyword": "Eggs and poultry [03.60.53],Farm register,Agrimonetary issues",
      "beneficiaryInstitution": null,
      "eventType": "AGR HOME",
      "afSigned": false,
      "ibuCasehandler": " ",
      "ibuCasehandlerEmail": null,
      "ibuCasehandlerPhone": null,
      "teamLeader": "Tatjana BORBAS",
      "teamLeaderEmail": "Tatjana.BORBAS@ec.europa.eu",
      "teamLeaderPhone": "+32 2 29 58951",
      "coCasehandler": " ",
      "coCasehandlerEmail": null,
      "coCasehandlerPhone": null,
      "countryEventPlace": "Portugal",
      "team": "AGR",
      "eventCategory": "Work from Home",
      "budgetGroup": "TO BE DEFINED",
      "taskNo": null,
      "eventGroup": "TAIEX standard",
      "afSignDate": null,
      "ofSignDate": null,
      "seriesOfEvent": null,
      "accountCaseHandler": " ",
      "accountCaseHandlerEmail": null,
      "accountCaseHandlerPhone": null,
      "ticketCoCaseHandler": " ",
      "ticketCoCaseHandlerEmail": null,
      "ticketCoCaseHandlerPhone": null,
      "afStatus": " ",
      "ofStatus": " ",
      "invoicePeriod": null,
      "motherEventId": 80032,
      "eventAddCorr": 0,
      "eventRemark": null,
      "eventStatusReport": null,
      "ofSubmissionDate": null,
      "project": "IPA, ENI",
      "lastWorkflowStep": "Active event",
      "taiexContractor": "TAIEX - 8",
      "externalRequestId": null
    },
    {
      "eventId": 80031,
      "eventName": "Workshop on Introduction to mindfulness",
      "euLegislation": "01 Free movement of goods (Partial),01.10 Internal market: approximation of laws [13.30] (Partial),01.10.15 Proprietary medicinal products [13.30.15] (Complete)",
      "city": "Bilbao",
      "startDate": 1598652000000,
      "startDateYear": 2020,
      "startDateMonth": 8,
      "endDate": 1598738400000,
      "createDate": 1594418400000,
      "ofSigned": false,
      "erSigned": " ",
      "beneficiary": "TO BE DEFINED",
      "eventKeyword": "Medical devices,Fertilisers",
      "beneficiaryInstitution": null,
      "eventType": "INT MARKT",
      "afSigned": false,
      "ibuCasehandler": "Tatjana BORBAS",
      "ibuCasehandlerEmail": "Tatjana.BORBAS@ec.europa.eu",
      "ibuCasehandlerPhone": "+32 2 29 58951",
      "teamLeader": "Helen LARSSON",
      "teamLeaderEmail": "Helen.LARSSON@ec.europa.eu",
      "teamLeaderPhone": "+32 2 29 91978",
      "coCasehandler": " ",
      "coCasehandlerEmail": null,
      "coCasehandlerPhone": null,
      "countryEventPlace": "Spain",
      "team": "INT MARKT",
      "eventCategory": "Workshop",
      "budgetGroup": "TO BE DEFINED",
      "taskNo": null,
      "eventGroup": "TAIEX standard",
      "afSignDate": null,
      "ofSignDate": null,
      "seriesOfEvent": null,
      "accountCaseHandler": " ",
      "accountCaseHandlerEmail": null,
      "accountCaseHandlerPhone": null,
      "ticketCoCaseHandler": " ",
      "ticketCoCaseHandlerEmail": null,
      "ticketCoCaseHandlerPhone": null,
      "afStatus": " ",
      "ofStatus": " ",
      "invoicePeriod": null,
      "motherEventId": 80031,
      "eventAddCorr": 0,
      "eventRemark": null,
      "eventStatusReport": null,
      "ofSubmissionDate": null,
      "project": "IPA, ENI",
      "lastWorkflowStep": "Active event",
      "taiexContractor": "TAIEX - 8",
      "externalRequestId": null
    },
    {
      "eventId": 80030,
      "eventName": "TO BE DEFINED",
      "euLegislation": "TAIEX procurements (Complete)",
      "city": "Brussels",
      "startDate": 4102441200000,
      "startDateYear": 2100,
      "startDateMonth": 1,
      "endDate": 4102441200000,
      "createDate": 1594332000000,
      "ofSigned": false,
      "erSigned": " ",
      "beneficiary": "TO BE DEFINED",
      "eventKeyword": "Report ",
      "beneficiaryInstitution": null,
      "eventType": "PROC",
      "afSigned": false,
      "ibuCasehandler": "Alin BEJENARU VRABIE",
      "ibuCasehandlerEmail": "Alin.BEJENARU@ext.ec.europa.eu",
      "ibuCasehandlerPhone": "+32 229-59593",
      "teamLeader": "Peter POLAJNAR",
      "teamLeaderEmail": "Peter.POLAJNAR@ec.europa.eu",
      "teamLeaderPhone": "+32 2 29 80146",
      "coCasehandler": " ",
      "coCasehandlerEmail": null,
      "coCasehandlerPhone": null,
      "countryEventPlace": "TAIEX Office",
      "team": "PROC",
      "eventCategory": "Procurement",
      "budgetGroup": "TO BE DEFINED",
      "taskNo": null,
      "eventGroup": "Other",
      "afSignDate": 1583507983000,
      "ofSignDate": null,
      "seriesOfEvent": null,
      "accountCaseHandler": " ",
      "accountCaseHandlerEmail": null,
      "accountCaseHandlerPhone": null,
      "ticketCoCaseHandler": " ",
      "ticketCoCaseHandlerEmail": null,
      "ticketCoCaseHandlerPhone": null,
      "afStatus": " ",
      "ofStatus": " ",
      "invoicePeriod": null,
      "motherEventId": 80030,
      "eventAddCorr": 0,
      "eventRemark": null,
      "eventStatusReport": null,
      "ofSubmissionDate": null,
      "project": "IPA, ENI",
      "lastWorkflowStep": "Draft Event",
      "taiexContractor": "TAIEX - 8",
      "externalRequestId": null
    },
    {
      "eventId": 80024,
      "eventName": "Dir TAIEX-8 contractor event",
      "euLegislation": "04 Free movement of capital [10.40] (Complete)",
      "city": "Brussels",
      "startDate": 1602108000000,
      "startDateYear": 2020,
      "startDateMonth": 10,
      "endDate": 1602194400000,
      "createDate": 1594332000000,
      "ofSigned": false,
      "erSigned": " ",
      "beneficiary": "TO BE DEFINED",
      "eventKeyword": "Crossborder payments",
      "beneficiaryInstitution": null,
      "eventType": "DIR",
      "afSigned": false,
      "ibuCasehandler": "Francesca CARPINELLA",
      "ibuCasehandlerEmail": "Francesca.CARPINELLA@ec.europa.eu",
      "ibuCasehandlerPhone": "13613",
      "teamLeader": "Peter POLAJNAR",
      "teamLeaderEmail": "Peter.POLAJNAR@ec.europa.eu",
      "teamLeaderPhone": "+32 2 29 80146",
      "coCasehandler": " ",
      "coCasehandlerEmail": null,
      "coCasehandlerPhone": null,
      "countryEventPlace": "TAIEX Office",
      "team": "PROC",
      "eventCategory": "Procurement",
      "budgetGroup": "TO BE DEFINED",
      "taskNo": null,
      "eventGroup": "TAIEX standard",
      "afSignDate": null,
      "ofSignDate": null,
      "seriesOfEvent": null,
      "accountCaseHandler": " ",
      "accountCaseHandlerEmail": null,
      "accountCaseHandlerPhone": null,
      "ticketCoCaseHandler": " ",
      "ticketCoCaseHandlerEmail": null,
      "ticketCoCaseHandlerPhone": null,
      "afStatus": " ",
      "ofStatus": " ",
      "invoicePeriod": null,
      "motherEventId": 80024,
      "eventAddCorr": 0,
      "eventRemark": null,
      "eventStatusReport": null,
      "ofSubmissionDate": null,
      "project": "IPA, ENI",
      "lastWorkflowStep": "Active event",
      "taiexContractor": "TAIEX - 8",
      "externalRequestId": null
    },
    {
      "eventId": 80023,
      "eventName": "TO BE DEFINED",
      "euLegislation": "16 Taxation [09] (Partial),16.30 Indirect taxation [09.30] (Partial),16.30.20 Excise duties [09.30.20] (Complete)",
      "city": "Podgorica",
      "startDate": 4102441200000,
      "startDateYear": 2100,
      "startDateMonth": 1,
      "endDate": 4102441200000,
      "createDate": 1594332000000,
      "ofSigned": false,
      "erSigned": " ",
      "beneficiary": "Montenegro",
      "eventKeyword": "Indirect taxation",
      "beneficiaryInstitution": "Customs Administration of Montenegro",
      "eventType": "INT MARKT IND/EXP",
      "afSigned": false,
      "ibuCasehandler": "Werner STAPPAERTS",
      "ibuCasehandlerEmail": "Werner.STAPPAERTS@ext.ec.europa.eu",
      "ibuCasehandlerPhone": "+32 229-96894",
      "teamLeader": "Helen LARSSON",
      "teamLeaderEmail": "Helen.LARSSON@ec.europa.eu",
      "teamLeaderPhone": "+32 2 29 91978",
      "coCasehandler": " ",
      "coCasehandlerEmail": null,
      "coCasehandlerPhone": null,
      "countryEventPlace": "Montenegro",
      "team": "INT MARKT",
      "eventCategory": "Expert Mission",
      "budgetGroup": "IPA",
      "taskNo": 31067,
      "eventGroup": "TAIEX standard",
      "afSignDate": 1579247879000,
      "ofSignDate": null,
      "seriesOfEvent": null,
      "accountCaseHandler": " ",
      "accountCaseHandlerEmail": null,
      "accountCaseHandlerPhone": null,
      "ticketCoCaseHandler": " ",
      "ticketCoCaseHandlerEmail": null,
      "ticketCoCaseHandlerPhone": null,
      "afStatus": " ",
      "ofStatus": " ",
      "invoicePeriod": null,
      "motherEventId": 80023,
      "eventAddCorr": 0,
      "eventRemark": null,
      "eventStatusReport": null,
      "ofSubmissionDate": null,
      "project": "IPA, ENI",
      "lastWorkflowStep": "Draft Event",
      "taiexContractor": "TAIEX - 8",
      "externalRequestId": null
    },
    {
      "eventId": 80018,
      "eventName": "DRAFT 31417 - TR - TAIEX Workshop on Treating and monitoring of wastewaters to be used for reclamation, irrigation and environmental enhancement purposes in the case of Covid-19 virus presenting in sanitatio",
      "euLegislation": "27 Environment [15] (Complete)",
      "city": " ",
      "startDate": 4102441200000,
      "startDateYear": 2100,
      "startDateMonth": 1,
      "endDate": 4102441200000,
      "createDate": 1594332000000,
      "ofSigned": false,
      "erSigned": " ",
      "beneficiary": "Turkey",
      "eventKeyword": "Chapter 27",
      "beneficiaryInstitution": null,
      "eventType": "ETT",
      "afSigned": false,
      "ibuCasehandler": "Francesca AQUARO",
      "ibuCasehandlerEmail": "Francesca.AQUARO@ec.europa.eu",
      "ibuCasehandlerPhone": "+32 2 29 96132",
      "teamLeader": "Scott BOWEN",
      "teamLeaderEmail": "Scott.BOWEN@ec.europa.eu",
      "teamLeaderPhone": "+32 229-56519",
      "coCasehandler": " ",
      "coCasehandlerEmail": null,
      "coCasehandlerPhone": null,
      "countryEventPlace": "TO BE DEFINED",
      "team": "ETT",
      "eventCategory": "Workshop",
      "budgetGroup": "IPA",
      "taskNo": 31417,
      "eventGroup": "TAIEX standard",
      "afSignDate": null,
      "ofSignDate": null,
      "seriesOfEvent": null,
      "accountCaseHandler": " ",
      "accountCaseHandlerEmail": null,
      "accountCaseHandlerPhone": null,
      "ticketCoCaseHandler": " ",
      "ticketCoCaseHandlerEmail": null,
      "ticketCoCaseHandlerPhone": null,
      "afStatus": " ",
      "ofStatus": " ",
      "invoicePeriod": null,
      "motherEventId": 80018,
      "eventAddCorr": 0,
      "eventRemark": null,
      "eventStatusReport": null,
      "ofSubmissionDate": null,
      "project": "IPA, ENI",
      "lastWorkflowStep": "Draft Event",
      "taiexContractor": "TAIEX - 8",
      "externalRequestId": null
    },
    {
      "eventId": 80017,
      "eventName": "DRAFT 31417 - TR - TAIEX Workshop on Treating and monitoring of wastewaters to be used for reclamation, irrigation and environmental enhancement purposes in the case of Covid-19 virus presenting in sanitatio",
      "euLegislation": "27 Environment [15] (Complete)",
      "city": " ",
      "startDate": 4102441200000,
      "startDateYear": 2100,
      "startDateMonth": 1,
      "endDate": 4102441200000,
      "createDate": 1594332000000,
      "ofSigned": false,
      "erSigned": " ",
      "beneficiary": "Turkey",
      "eventKeyword": "COVID 19",
      "beneficiaryInstitution": null,
      "eventType": "ETT",
      "afSigned": false,
      "ibuCasehandler": "Tania ANGUELOVA",
      "ibuCasehandlerEmail": "Tania.ANGUELOVA@ec.europa.eu",
      "ibuCasehandlerPhone": "56360",
      "teamLeader": "Scott BOWEN",
      "teamLeaderEmail": "Scott.BOWEN@ec.europa.eu",
      "teamLeaderPhone": "+32 229-56519",
      "coCasehandler": " ",
      "coCasehandlerEmail": null,
      "coCasehandlerPhone": null,
      "countryEventPlace": "TO BE DEFINED",
      "team": "ETT",
      "eventCategory": "Workshop",
      "budgetGroup": "IPA",
      "taskNo": 31417,
      "eventGroup": "TAIEX standard",
      "afSignDate": null,
      "ofSignDate": null,
      "seriesOfEvent": null,
      "accountCaseHandler": " ",
      "accountCaseHandlerEmail": null,
      "accountCaseHandlerPhone": null,
      "ticketCoCaseHandler": " ",
      "ticketCoCaseHandlerEmail": null,
      "ticketCoCaseHandlerPhone": null,
      "afStatus": " ",
      "ofStatus": " ",
      "invoicePeriod": null,
      "motherEventId": 80017,
      "eventAddCorr": 0,
      "eventRemark": null,
      "eventStatusReport": null,
      "ofSubmissionDate": null,
      "project": "IPA, ENI",
      "lastWorkflowStep": "Draft Event",
      "taiexContractor": "TAIEX - 8",
      "externalRequestId": null
    },
    {
      "eventId": 80016,
      "eventName": "DRAFT 31417 - TR - TAIEX Workshop on Treating and monitoring of wastewaters to be used for reclamation, irrigation and environmental enhancement purposes in the case of Covid-19 virus presenting in sanitatio",
      "euLegislation": "27 Environment [15] (Complete)",
      "city": " ",
      "startDate": 4102441200000,
      "startDateYear": 2100,
      "startDateMonth": 1,
      "endDate": 4102441200000,
      "createDate": 1594332000000,
      "ofSigned": false,
      "erSigned": " ",
      "beneficiary": "Turkey",
      "eventKeyword": "TO BE DEFINED",
      "beneficiaryInstitution": null,
      "eventType": "ETT",
      "afSigned": false,
      "ibuCasehandler": " ",
      "ibuCasehandlerEmail": null,
      "ibuCasehandlerPhone": null,
      "teamLeader": "Scott BOWEN",
      "teamLeaderEmail": "Scott.BOWEN@ec.europa.eu",
      "teamLeaderPhone": "+32 229-56519",
      "coCasehandler": " ",
      "coCasehandlerEmail": null,
      "coCasehandlerPhone": null,
      "countryEventPlace": "TO BE DEFINED",
      "team": "ETT",
      "eventCategory": "Workshop",
      "budgetGroup": "IPA",
      "taskNo": 31417,
      "eventGroup": "TAIEX standard",
      "afSignDate": null,
      "ofSignDate": null,
      "seriesOfEvent": null,
      "accountCaseHandler": " ",
      "accountCaseHandlerEmail": null,
      "accountCaseHandlerPhone": null,
      "ticketCoCaseHandler": " ",
      "ticketCoCaseHandlerEmail": null,
      "ticketCoCaseHandlerPhone": null,
      "afStatus": " ",
      "ofStatus": " ",
      "invoicePeriod": null,
      "motherEventId": 80016,
      "eventAddCorr": 0,
      "eventRemark": null,
      "eventStatusReport": null,
      "ofSubmissionDate": null,
      "project": "IPA, ENI",
      "lastWorkflowStep": "Draft Event",
      "taiexContractor": "TAIEX - 8",
      "externalRequestId": null
    },
    {
      "eventId": 80015,
      "eventName": "DRAFT 31417 - TR - TAIEX Workshop on Treating and monitoring of wastewaters to be used for reclamation, irrigation and environmental enhancement purposes in the case of Covid-19 virus presenting in sanitatio",
      "euLegislation": "27 Environment [15] (Complete)",
      "city": "Ademuz",
      "startDate": 4102441200000,
      "startDateYear": 2100,
      "startDateMonth": 1,
      "endDate": 4102441200000,
      "createDate": 1594332000000,
      "ofSigned": false,
      "erSigned": " ",
      "beneficiary": "Turkey",
      "eventKeyword": "Air",
      "beneficiaryInstitution": null,
      "eventType": "ETT",
      "afSigned": false,
      "ibuCasehandler": "Tania ANGUELOVA",
      "ibuCasehandlerEmail": "Tania.ANGUELOVA@ec.europa.eu",
      "ibuCasehandlerPhone": "56360",
      "teamLeader": "Scott BOWEN",
      "teamLeaderEmail": "Scott.BOWEN@ec.europa.eu",
      "teamLeaderPhone": "+32 229-56519",
      "coCasehandler": " ",
      "coCasehandlerEmail": null,
      "coCasehandlerPhone": null,
      "countryEventPlace": "Spain",
      "team": "ETT",
      "eventCategory": "Workshop",
      "budgetGroup": "IPA",
      "taskNo": 31417,
      "eventGroup": "TAIEX standard",
      "afSignDate": null,
      "ofSignDate": null,
      "seriesOfEvent": null,
      "accountCaseHandler": " ",
      "accountCaseHandlerEmail": null,
      "accountCaseHandlerPhone": null,
      "ticketCoCaseHandler": " ",
      "ticketCoCaseHandlerEmail": null,
      "ticketCoCaseHandlerPhone": null,
      "afStatus": " ",
      "ofStatus": " ",
      "invoicePeriod": null,
      "motherEventId": 80015,
      "eventAddCorr": 0,
      "eventRemark": null,
      "eventStatusReport": null,
      "ofSubmissionDate": null,
      "project": "IPA, ENI",
      "lastWorkflowStep": "Draft Event",
      "taiexContractor": "TAIEX - 8",
      "externalRequestId": null
    },
    {
      "eventId": 80014,
      "eventName": "DRAFT 31418 - TR - Expert Mission on Analysis of the Impacts and Risk Assessment of Covid-19 on the seed sector The activity is an expert mission; to carry out an analysis of the Impacts and Risk Assessment of Covid-19 on the seed sector for the resilience  of farmers and stakeholders for food insecurity  and upcoming food safety problems in the future and to prepare a report for solving the ",
      "euLegislation": "11 Agriculture and rural development [03] (Complete),12 Food safety, veterinary and phytosanitary policy (Complete)",
      "city": "Abbotsford, Johannesburg",
      "startDate": 4102441200000,
      "startDateYear": 2100,
      "startDateMonth": 1,
      "endDate": 4102441200000,
      "createDate": 1594332000000,
      "ofSigned": false,
      "erSigned": " ",
      "beneficiary": "Turkey",
      "eventKeyword": "Additives authorised and purity criteria",
      "beneficiaryInstitution": null,
      "eventType": "AGR IND/EXP",
      "afSigned": false,
      "ibuCasehandler": "Tania ANGUELOVA",
      "ibuCasehandlerEmail": "Tania.ANGUELOVA@ec.europa.eu",
      "ibuCasehandlerPhone": "56360",
      "teamLeader": "Tatjana BORBAS",
      "teamLeaderEmail": "Tatjana.BORBAS@ec.europa.eu",
      "teamLeaderPhone": "+32 2 29 58951",
      "coCasehandler": " ",
      "coCasehandlerEmail": null,
      "coCasehandlerPhone": null,
      "countryEventPlace": "South Africa",
      "team": "AGR",
      "eventCategory": "Expert Mission",
      "budgetGroup": "IPA",
      "taskNo": 31418,
      "eventGroup": "TAIEX standard",
      "afSignDate": null,
      "ofSignDate": null,
      "seriesOfEvent": null,
      "accountCaseHandler": " ",
      "accountCaseHandlerEmail": null,
      "accountCaseHandlerPhone": null,
      "ticketCoCaseHandler": " ",
      "ticketCoCaseHandlerEmail": null,
      "ticketCoCaseHandlerPhone": null,
      "afStatus": " ",
      "ofStatus": " ",
      "invoicePeriod": null,
      "motherEventId": 80014,
      "eventAddCorr": 0,
      "eventRemark": null,
      "eventStatusReport": null,
      "ofSubmissionDate": null,
      "project": "IPA, ENI",
      "lastWorkflowStep": "Draft Event",
      "taiexContractor": "TAIEX - 8",
      "externalRequestId": null
    },
    {
      "eventId": 80012,
      "eventName": "TO BE DEFINED",
      "euLegislation": "10 Information society and media (Partial),10.10 Information technology, telecommunications and data-processing [13.20.60] (Complete)",
      "city": "Tallinn",
      "startDate": 4102441200000,
      "startDateYear": 2100,
      "startDateMonth": 1,
      "endDate": 4102441200000,
      "createDate": 1594332000000,
      "ofSigned": false,
      "erSigned": " ",
      "beneficiary": "TO BE DEFINED",
      "eventKeyword": "Chapter 10,Deliverable - Good Governance,Deliverable - Connectivity",
      "beneficiaryInstitution": "National Regulator Authorities, Directorate General Communications Networks, ",
      "eventType": "ETT HOME",
      "afSigned": false,
      "ibuCasehandler": "Fanny MARCHAL",
      "ibuCasehandlerEmail": "Fanny.MARCHAL@ec.europa.eu",
      "ibuCasehandlerPhone": "+32 2 29 58451",
      "teamLeader": "Scott BOWEN",
      "teamLeaderEmail": "Scott.BOWEN@ec.europa.eu",
      "teamLeaderPhone": "+32 229-56519",
      "coCasehandler": " ",
      "coCasehandlerEmail": null,
      "coCasehandlerPhone": null,
      "countryEventPlace": "Estonia",
      "team": "ETT",
      "eventCategory": "Work from Home",
      "budgetGroup": "TO BE DEFINED",
      "taskNo": 31354,
      "eventGroup": "Part of a Series",
      "afSignDate": 1587979634000,
      "ofSignDate": null,
      "seriesOfEvent": "ETT WFH COVID 19",
      "accountCaseHandler": " ",
      "accountCaseHandlerEmail": null,
      "accountCaseHandlerPhone": null,
      "ticketCoCaseHandler": " ",
      "ticketCoCaseHandlerEmail": null,
      "ticketCoCaseHandlerPhone": null,
      "afStatus": " ",
      "ofStatus": " ",
      "invoicePeriod": null,
      "motherEventId": 80012,
      "eventAddCorr": 0,
      "eventRemark": null,
      "eventStatusReport": null,
      "ofSubmissionDate": null,
      "project": "IPA, ENI",
      "lastWorkflowStep": "Draft Event",
      "taiexContractor": "TAIEX - 8",
      "externalRequestId": null
    },
    {
      "eventId": 80011,
      "eventName": "TO BE DEFINED",
      "euLegislation": "10 Information society and media (Partial),10.10 Information technology, telecommunications and data-processing [13.20.60] (Complete)",
      "city": "Tallinn",
      "startDate": 4102441200000,
      "startDateYear": 2100,
      "startDateMonth": 1,
      "endDate": 4102441200000,
      "createDate": 1594332000000,
      "ofSigned": false,
      "erSigned": " ",
      "beneficiary": "TO BE DEFINED",
      "eventKeyword": "Chapter 10,Deliverable - Good Governance,Deliverable - Connectivity",
      "beneficiaryInstitution": "National Regulator Authorities, Directorate General Communications Networks, ",
      "eventType": "ETT HOME",
      "afSigned": false,
      "ibuCasehandler": "Alin BEJENARU VRABIE",
      "ibuCasehandlerEmail": "Alin.BEJENARU@ext.ec.europa.eu",
      "ibuCasehandlerPhone": "+32 229-59593",
      "teamLeader": "Scott BOWEN",
      "teamLeaderEmail": "Scott.BOWEN@ec.europa.eu",
      "teamLeaderPhone": "+32 229-56519",
      "coCasehandler": " ",
      "coCasehandlerEmail": null,
      "coCasehandlerPhone": null,
      "countryEventPlace": "Estonia",
      "team": "ETT",
      "eventCategory": "Work from Home",
      "budgetGroup": "TO BE DEFINED",
      "taskNo": 31354,
      "eventGroup": "Part of a Series",
      "afSignDate": 1587979634000,
      "ofSignDate": null,
      "seriesOfEvent": "ETT WFH COVID 19",
      "accountCaseHandler": " ",
      "accountCaseHandlerEmail": null,
      "accountCaseHandlerPhone": null,
      "ticketCoCaseHandler": " ",
      "ticketCoCaseHandlerEmail": null,
      "ticketCoCaseHandlerPhone": null,
      "afStatus": " ",
      "ofStatus": " ",
      "invoicePeriod": null,
      "motherEventId": 80011,
      "eventAddCorr": 0,
      "eventRemark": null,
      "eventStatusReport": null,
      "ofSubmissionDate": null,
      "project": "IPA, ENI",
      "lastWorkflowStep": "Draft Event",
      "taiexContractor": "TAIEX - 8",
      "externalRequestId": null
    },
    {
      "eventId": 80010,
      "eventName": "TO BE DEFINED",
      "euLegislation": "10 Information society and media (Partial),10.10 Information technology, telecommunications and data-processing [13.20.60] (Complete)",
      "city": "Tallinn",
      "startDate": 4102441200000,
      "startDateYear": 2100,
      "startDateMonth": 1,
      "endDate": 4102441200000,
      "createDate": 1594332000000,
      "ofSigned": false,
      "erSigned": " ",
      "beneficiary": "TO BE DEFINED",
      "eventKeyword": "Chapter 10,Deliverable - Good Governance,Deliverable - Connectivity",
      "beneficiaryInstitution": "National Regulator Authorities, Directorate General Communications Networks, ",
      "eventType": "ETT HOME",
      "afSigned": false,
      "ibuCasehandler": "Alin BEJENARU VRABIE",
      "ibuCasehandlerEmail": "Alin.BEJENARU@ext.ec.europa.eu",
      "ibuCasehandlerPhone": "+32 229-59593",
      "teamLeader": "Scott BOWEN",
      "teamLeaderEmail": "Scott.BOWEN@ec.europa.eu",
      "teamLeaderPhone": "+32 229-56519",
      "coCasehandler": " ",
      "coCasehandlerEmail": null,
      "coCasehandlerPhone": null,
      "countryEventPlace": "Estonia",
      "team": "ETT",
      "eventCategory": "Work from Home",
      "budgetGroup": "TO BE DEFINED",
      "taskNo": 31354,
      "eventGroup": "Part of a Series",
      "afSignDate": 1587979634000,
      "ofSignDate": null,
      "seriesOfEvent": "ETT WFH COVID 19",
      "accountCaseHandler": " ",
      "accountCaseHandlerEmail": null,
      "accountCaseHandlerPhone": null,
      "ticketCoCaseHandler": " ",
      "ticketCoCaseHandlerEmail": null,
      "ticketCoCaseHandlerPhone": null,
      "afStatus": " ",
      "ofStatus": " ",
      "invoicePeriod": null,
      "motherEventId": 80010,
      "eventAddCorr": 0,
      "eventRemark": null,
      "eventStatusReport": null,
      "ofSubmissionDate": null,
      "project": "IPA, ENI",
      "lastWorkflowStep": "Draft Event",
      "taiexContractor": "TAIEX - 8",
      "externalRequestId": null
    },
    {
      "eventId": 80009,
      "eventName": "TO BE DEFINED",
      "euLegislation": "27 Environment [15] (Partial),27.10 Environment [15.10] (Partial),27.10.20 Pollution and nuisances [15.10.20] (Partial),27.10.20.30 Monitoring of atmospheric pollution [15.10.20.30] (Complete)",
      "city": "Video Tele Conference ",
      "startDate": 4102441200000,
      "startDateYear": 2100,
      "startDateMonth": 1,
      "endDate": 4102441200000,
      "createDate": 1594332000000,
      "ofSigned": false,
      "erSigned": " ",
      "beneficiary": "TO BE DEFINED",
      "eventKeyword": "Air",
      "beneficiaryInstitution": "Line Ministries in EPPA Beneficiary Countries (responsible for environmental policies)",
      "eventType": "EPPA",
      "afSigned": false,
      "ibuCasehandler": "Alin BEJENARU VRABIE",
      "ibuCasehandlerEmail": "Alin.BEJENARU@ext.ec.europa.eu",
      "ibuCasehandlerPhone": "+32 229-59593",
      "teamLeader": "Scott BOWEN",
      "teamLeaderEmail": "Scott.BOWEN@ec.europa.eu",
      "teamLeaderPhone": "+32 229-56519",
      "coCasehandler": " ",
      "coCasehandlerEmail": null,
      "coCasehandlerPhone": null,
      "countryEventPlace": "EU Institution",
      "team": "ETT",
      "eventCategory": "Workshop",
      "budgetGroup": "TO BE DEFINED",
      "taskNo": 31363,
      "eventGroup": "TAIEX strategic",
      "afSignDate": 1589907672000,
      "ofSignDate": null,
      "seriesOfEvent": null,
      "accountCaseHandler": " ",
      "accountCaseHandlerEmail": null,
      "accountCaseHandlerPhone": null,
      "ticketCoCaseHandler": " ",
      "ticketCoCaseHandlerEmail": null,
      "ticketCoCaseHandlerPhone": null,
      "afStatus": " ",
      "ofStatus": " ",
      "invoicePeriod": null,
      "motherEventId": 80009,
      "eventAddCorr": 0,
      "eventRemark": null,
      "eventStatusReport": null,
      "ofSubmissionDate": null,
      "project": "IPA, ENI",
      "lastWorkflowStep": "Draft Event",
      "taiexContractor": "TAIEX - 8",
      "externalRequestId": null
    },
    {
      "eventId": 80008,
      "eventName": "TO BE DEFINED",
      "euLegislation": "27 Environment [15] (Partial),27.10 Environment [15.10] (Partial),27.10.20 Pollution and nuisances [15.10.20] (Partial),27.10.20.30 Monitoring of atmospheric pollution [15.10.20.30] (Complete)",
      "city": "Video Tele Conference ",
      "startDate": 4102441200000,
      "startDateYear": 2100,
      "startDateMonth": 1,
      "endDate": 4102441200000,
      "createDate": 1594332000000,
      "ofSigned": false,
      "erSigned": " ",
      "beneficiary": "TO BE DEFINED",
      "eventKeyword": "Air",
      "beneficiaryInstitution": "Line Ministries in EPPA Beneficiary Countries (responsible for environmental policies)",
      "eventType": "EPPA",
      "afSigned": false,
      "ibuCasehandler": "Alin BEJENARU VRABIE",
      "ibuCasehandlerEmail": "Alin.BEJENARU@ext.ec.europa.eu",
      "ibuCasehandlerPhone": "+32 229-59593",
      "teamLeader": "Scott BOWEN",
      "teamLeaderEmail": "Scott.BOWEN@ec.europa.eu",
      "teamLeaderPhone": "+32 229-56519",
      "coCasehandler": " ",
      "coCasehandlerEmail": null,
      "coCasehandlerPhone": null,
      "countryEventPlace": "EU Institution",
      "team": "ETT",
      "eventCategory": "Workshop",
      "budgetGroup": "TO BE DEFINED",
      "taskNo": 31363,
      "eventGroup": "TAIEX strategic",
      "afSignDate": 1589907672000,
      "ofSignDate": null,
      "seriesOfEvent": null,
      "accountCaseHandler": " ",
      "accountCaseHandlerEmail": null,
      "accountCaseHandlerPhone": null,
      "ticketCoCaseHandler": " ",
      "ticketCoCaseHandlerEmail": null,
      "ticketCoCaseHandlerPhone": null,
      "afStatus": " ",
      "ofStatus": " ",
      "invoicePeriod": null,
      "motherEventId": 80008,
      "eventAddCorr": 0,
      "eventRemark": null,
      "eventStatusReport": null,
      "ofSubmissionDate": null,
      "project": "IPA, ENI",
      "lastWorkflowStep": "Draft Event",
      "taiexContractor": "TAIEX - 8",
      "externalRequestId": null
    },
    {
      "eventId": 80005,
      "eventName": "TO BE DEFINED",
      "euLegislation": "10 Information society and media (Partial),10.10 Information technology, telecommunications and data-processing [13.20.60] (Complete)",
      "city": "Tallinn",
      "startDate": 4102441200000,
      "startDateYear": 2100,
      "startDateMonth": 1,
      "endDate": 4102441200000,
      "createDate": 1594332000000,
      "ofSigned": false,
      "erSigned": " ",
      "beneficiary": "TO BE DEFINED",
      "eventKeyword": "Chapter 10,Deliverable - Good Governance,Deliverable - Connectivity",
      "beneficiaryInstitution": "National Regulator Authorities, Directorate General Communications Networks, ",
      "eventType": "ETT HOME",
      "afSigned": false,
      "ibuCasehandler": "Alin BEJENARU VRABIE",
      "ibuCasehandlerEmail": "Alin.BEJENARU@ext.ec.europa.eu",
      "ibuCasehandlerPhone": "+32 229-59593",
      "teamLeader": "Scott BOWEN",
      "teamLeaderEmail": "Scott.BOWEN@ec.europa.eu",
      "teamLeaderPhone": "+32 229-56519",
      "coCasehandler": " ",
      "coCasehandlerEmail": null,
      "coCasehandlerPhone": null,
      "countryEventPlace": "Estonia",
      "team": "ETT",
      "eventCategory": "Work from Home",
      "budgetGroup": "TO BE DEFINED",
      "taskNo": 31354,
      "eventGroup": "Part of a Series",
      "afSignDate": 1587979634000,
      "ofSignDate": null,
      "seriesOfEvent": "ETT WFH COVID 19",
      "accountCaseHandler": " ",
      "accountCaseHandlerEmail": null,
      "accountCaseHandlerPhone": null,
      "ticketCoCaseHandler": " ",
      "ticketCoCaseHandlerEmail": null,
      "ticketCoCaseHandlerPhone": null,
      "afStatus": " ",
      "ofStatus": " ",
      "invoicePeriod": null,
      "motherEventId": 80005,
      "eventAddCorr": 0,
      "eventRemark": null,
      "eventStatusReport": null,
      "ofSubmissionDate": null,
      "project": "IPA, ENI",
      "lastWorkflowStep": "Draft Event",
      "taiexContractor": "TAIEX - 8",
      "externalRequestId": null
    },
    {
      "eventId": 80004,
      "eventName": "tes taiex 8 alin",
      "euLegislation": "04 Free movement of capital [10.40] (Complete)",
      "city": " ",
      "startDate": 1597183200000,
      "startDateYear": 2020,
      "startDateMonth": 8,
      "endDate": 1597269600000,
      "createDate": 1594245600000,
      "ofSigned": false,
      "erSigned": " ",
      "beneficiary": "TO BE DEFINED",
      "eventKeyword": "TO BE DEFINED",
      "beneficiaryInstitution": null,
      "eventType": "AGR",
      "afSigned": false,
      "ibuCasehandler": " ",
      "ibuCasehandlerEmail": null,
      "ibuCasehandlerPhone": null,
      "teamLeader": "Tatjana BORBAS",
      "teamLeaderEmail": "Tatjana.BORBAS@ec.europa.eu",
      "teamLeaderPhone": "+32 2 29 58951",
      "coCasehandler": " ",
      "coCasehandlerEmail": null,
      "coCasehandlerPhone": null,
      "countryEventPlace": "Spain",
      "team": "AGR",
      "eventCategory": "Workshop",
      "budgetGroup": "TO BE DEFINED",
      "taskNo": null,
      "eventGroup": "TAIEX standard",
      "afSignDate": null,
      "ofSignDate": null,
      "seriesOfEvent": null,
      "accountCaseHandler": " ",
      "accountCaseHandlerEmail": null,
      "accountCaseHandlerPhone": null,
      "ticketCoCaseHandler": " ",
      "ticketCoCaseHandlerEmail": null,
      "ticketCoCaseHandlerPhone": null,
      "afStatus": " ",
      "ofStatus": " ",
      "invoicePeriod": null,
      "motherEventId": 80004,
      "eventAddCorr": 0,
      "eventRemark": null,
      "eventStatusReport": null,
      "ofSubmissionDate": null,
      "project": "IPA, ENI",
      "lastWorkflowStep": "Active event",
      "taiexContractor": "TAIEX - 8",
      "externalRequestId": null
    },
    {
      "eventId": 80003,
      "eventName": "test proc web folder structure alin TAIEX 7",
      "euLegislation": "TO BE DEFINED",
      "city": " ",
      "startDate": 1597183200000,
      "startDateYear": 2020,
      "startDateMonth": 8,
      "endDate": 1597269600000,
      "createDate": 1594245600000,
      "ofSigned": false,
      "erSigned": " ",
      "beneficiary": "TO BE DEFINED",
      "eventKeyword": "TO BE DEFINED",
      "beneficiaryInstitution": null,
      "eventType": "AGR",
      "afSigned": false,
      "ibuCasehandler": " ",
      "ibuCasehandlerEmail": null,
      "ibuCasehandlerPhone": null,
      "teamLeader": "Tatjana BORBAS",
      "teamLeaderEmail": "Tatjana.BORBAS@ec.europa.eu",
      "teamLeaderPhone": "+32 2 29 58951",
      "coCasehandler": " ",
      "coCasehandlerEmail": null,
      "coCasehandlerPhone": null,
      "countryEventPlace": "Spain",
      "team": "AGR",
      "eventCategory": "Workshop",
      "budgetGroup": "TO BE DEFINED",
      "taskNo": null,
      "eventGroup": "TAIEX standard",
      "afSignDate": null,
      "ofSignDate": null,
      "seriesOfEvent": null,
      "accountCaseHandler": " ",
      "accountCaseHandlerEmail": null,
      "accountCaseHandlerPhone": null,
      "ticketCoCaseHandler": " ",
      "ticketCoCaseHandlerEmail": null,
      "ticketCoCaseHandlerPhone": null,
      "afStatus": " ",
      "ofStatus": " ",
      "invoicePeriod": null,
      "motherEventId": 80003,
      "eventAddCorr": 0,
      "eventRemark": null,
      "eventStatusReport": null,
      "ofSubmissionDate": null,
      "project": "IPA, ENI",
      "lastWorkflowStep": "Active event",
      "taiexContractor": "TAIEX - 8",
      "externalRequestId": null
    },
    {
      "eventId": 80002,
      "eventName": "test proc web folder structure alin TAIEX 7",
      "euLegislation": "TO BE DEFINED",
      "city": " ",
      "startDate": 1597183200000,
      "startDateYear": 2020,
      "startDateMonth": 8,
      "endDate": 1597269600000,
      "createDate": 1594245600000,
      "ofSigned": false,
      "erSigned": " ",
      "beneficiary": "TO BE DEFINED",
      "eventKeyword": "TO BE DEFINED",
      "beneficiaryInstitution": null,
      "eventType": "AGR",
      "afSigned": false,
      "ibuCasehandler": " ",
      "ibuCasehandlerEmail": null,
      "ibuCasehandlerPhone": null,
      "teamLeader": "Tatjana BORBAS",
      "teamLeaderEmail": "Tatjana.BORBAS@ec.europa.eu",
      "teamLeaderPhone": "+32 2 29 58951",
      "coCasehandler": " ",
      "coCasehandlerEmail": null,
      "coCasehandlerPhone": null,
      "countryEventPlace": "Spain",
      "team": "AGR",
      "eventCategory": "Workshop",
      "budgetGroup": "TO BE DEFINED",
      "taskNo": null,
      "eventGroup": "TAIEX standard",
      "afSignDate": null,
      "ofSignDate": null,
      "seriesOfEvent": null,
      "accountCaseHandler": " ",
      "accountCaseHandlerEmail": null,
      "accountCaseHandlerPhone": null,
      "ticketCoCaseHandler": " ",
      "ticketCoCaseHandlerEmail": null,
      "ticketCoCaseHandlerPhone": null,
      "afStatus": " ",
      "ofStatus": " ",
      "invoicePeriod": null,
      "motherEventId": 80002,
      "eventAddCorr": 0,
      "eventRemark": null,
      "eventStatusReport": null,
      "ofSubmissionDate": null,
      "project": "IPA, ENI",
      "lastWorkflowStep": "Active event",
      "taiexContractor": "TAIEX - 8",
      "externalRequestId": null
    },
    {
      "eventId": 80001,
      "eventName": "tes taiex 8 alin",
      "euLegislation": "04 Free movement of capital [10.40] (Complete)",
      "city": " ",
      "startDate": 1597183200000,
      "startDateYear": 2020,
      "startDateMonth": 8,
      "endDate": 1597269600000,
      "createDate": 1594245600000,
      "ofSigned": false,
      "erSigned": " ",
      "beneficiary": "TO BE DEFINED",
      "eventKeyword": "COVID 19",
      "beneficiaryInstitution": null,
      "eventType": "AGR IND/EXP",
      "afSigned": false,
      "ibuCasehandler": "Tania ANGUELOVA",
      "ibuCasehandlerEmail": "Tania.ANGUELOVA@ec.europa.eu",
      "ibuCasehandlerPhone": "56360",
      "teamLeader": "Tatjana BORBAS",
      "teamLeaderEmail": "Tatjana.BORBAS@ec.europa.eu",
      "teamLeaderPhone": "+32 2 29 58951",
      "coCasehandler": " ",
      "coCasehandlerEmail": null,
      "coCasehandlerPhone": null,
      "countryEventPlace": "Somalia",
      "team": "AGR",
      "eventCategory": "Expert Mission",
      "budgetGroup": "TO BE DEFINED",
      "taskNo": null,
      "eventGroup": "TAIEX standard",
      "afSignDate": null,
      "ofSignDate": null,
      "seriesOfEvent": null,
      "accountCaseHandler": " ",
      "accountCaseHandlerEmail": null,
      "accountCaseHandlerPhone": null,
      "ticketCoCaseHandler": " ",
      "ticketCoCaseHandlerEmail": null,
      "ticketCoCaseHandlerPhone": null,
      "afStatus": " ",
      "ofStatus": " ",
      "invoicePeriod": null,
      "motherEventId": 80001,
      "eventAddCorr": 0,
      "eventRemark": null,
      "eventStatusReport": null,
      "ofSubmissionDate": null,
      "project": "IPA, ENI",
      "lastWorkflowStep": "Active event",
      "taiexContractor": "TAIEX - 8",
      "externalRequestId": null
    },
    {
      "eventId": 80000,
      "eventName": "test proc web folder structure alin TAIEX 7",
      "euLegislation": "04 Free movement of capital [10.40] (Complete)",
      "city": " ",
      "startDate": 1597183200000,
      "startDateYear": 2020,
      "startDateMonth": 8,
      "endDate": 1597269600000,
      "createDate": 1594245600000,
      "ofSigned": false,
      "erSigned": " ",
      "beneficiary": "TO BE DEFINED",
      "eventKeyword": "COVID 19",
      "beneficiaryInstitution": null,
      "eventType": "AGR",
      "afSigned": false,
      "ibuCasehandler": "Francesca AQUARO",
      "ibuCasehandlerEmail": "Francesca.AQUARO@ec.europa.eu",
      "ibuCasehandlerPhone": "+32 2 29 96132",
      "teamLeader": "Tatjana BORBAS",
      "teamLeaderEmail": "Tatjana.BORBAS@ec.europa.eu",
      "teamLeaderPhone": "+32 2 29 58951",
      "coCasehandler": " ",
      "coCasehandlerEmail": null,
      "coCasehandlerPhone": null,
      "countryEventPlace": "Spain",
      "team": "AGR",
      "eventCategory": "Workshop",
      "budgetGroup": "TO BE DEFINED",
      "taskNo": null,
      "eventGroup": "TAIEX standard",
      "afSignDate": null,
      "ofSignDate": null,
      "seriesOfEvent": null,
      "accountCaseHandler": " ",
      "accountCaseHandlerEmail": null,
      "accountCaseHandlerPhone": null,
      "ticketCoCaseHandler": " ",
      "ticketCoCaseHandlerEmail": null,
      "ticketCoCaseHandlerPhone": null,
      "afStatus": " ",
      "ofStatus": " ",
      "invoicePeriod": null,
      "motherEventId": 80000,
      "eventAddCorr": 0,
      "eventRemark": null,
      "eventStatusReport": null,
      "ofSubmissionDate": null,
      "project": "IPA, ENI",
      "lastWorkflowStep": "Active event",
      "taiexContractor": "TAIEX - 8",
      "externalRequestId": null
    },
    {
      "eventId": 71111,
      "eventName": "TO BE DEFINED",
      "euLegislation": "10 Information society and media (Partial),10.10 Information technology, telecommunications and data-processing [13.20.60] (Complete)",
      "city": "Tallinn",
      "startDate": 4102441200000,
      "startDateYear": 2100,
      "startDateMonth": 1,
      "endDate": 4102441200000,
      "createDate": 1594332000000,
      "ofSigned": false,
      "erSigned": " ",
      "beneficiary": "TO BE DEFINED",
      "eventKeyword": "Chapter 10,Deliverable - Good Governance,Deliverable - Connectivity",
      "beneficiaryInstitution": "National Regulator Authorities, Directorate General Communications Networks, ",
      "eventType": "ETT HOME",
      "afSigned": false,
      "ibuCasehandler": "Emilija Pavlovska",
      "ibuCasehandlerEmail": "pavlovska@ibf.be",
      "ibuCasehandlerPhone": "+32 2 237 09 62",
      "teamLeader": "Scott BOWEN",
      "teamLeaderEmail": "Scott.BOWEN@ec.europa.eu",
      "teamLeaderPhone": "+32 229-56519",
      "coCasehandler": " ",
      "coCasehandlerEmail": null,
      "coCasehandlerPhone": null,
      "countryEventPlace": "Estonia",
      "team": "ETT",
      "eventCategory": "Work from Home",
      "budgetGroup": "TO BE DEFINED",
      "taskNo": 31354,
      "eventGroup": "Part of a Series",
      "afSignDate": 1587979634000,
      "ofSignDate": null,
      "seriesOfEvent": "ETT WFH COVID 19",
      "accountCaseHandler": " ",
      "accountCaseHandlerEmail": null,
      "accountCaseHandlerPhone": null,
      "ticketCoCaseHandler": " ",
      "ticketCoCaseHandlerEmail": null,
      "ticketCoCaseHandlerPhone": null,
      "afStatus": " ",
      "ofStatus": " ",
      "invoicePeriod": null,
      "motherEventId": 71111,
      "eventAddCorr": 0,
      "eventRemark": null,
      "eventStatusReport": null,
      "ofSubmissionDate": null,
      "project": "IPA, ENI",
      "lastWorkflowStep": "Draft Event",
      "taiexContractor": "IBF - 7",
      "externalRequestId": null
    },
    {
      "eventId": 70698,
      "eventName": "DRAFT 31422 - GE - TAIEX Expert Mission on Neutral Public Internet Exchange Point (IXP) – ensuring/facilitating access to high-bandwidth and low-latency Internet within Covid-1",
      "euLegislation": "35 Other issues (Complete)",
      "city": " ",
      "startDate": 4102441200000,
      "startDateYear": 2100,
      "startDateMonth": 1,
      "endDate": 4102441200000,
      "createDate": 1594245600000,
      "ofSigned": false,
      "erSigned": " ",
      "beneficiary": "Georgia",
      "eventKeyword": "COVID 19",
      "beneficiaryInstitution": "Georgian National Communications Commission (GNCC)",
      "eventType": "ETT IND/EXP",
      "afSigned": false,
      "ibuCasehandler": " ",
      "ibuCasehandlerEmail": null,
      "ibuCasehandlerPhone": null,
      "teamLeader": "Scott BOWEN",
      "teamLeaderEmail": "Scott.BOWEN@ec.europa.eu",
      "teamLeaderPhone": "+32 229-56519",
      "coCasehandler": " ",
      "coCasehandlerEmail": null,
      "coCasehandlerPhone": null,
      "countryEventPlace": "Croatia",
      "team": "ETT",
      "eventCategory": "Expert Mission",
      "budgetGroup": "ENPI EAST",
      "taskNo": 31422,
      "eventGroup": "TAIEX standard",
      "afSignDate": null,
      "ofSignDate": null,
      "seriesOfEvent": null,
      "accountCaseHandler": " ",
      "accountCaseHandlerEmail": null,
      "accountCaseHandlerPhone": null,
      "ticketCoCaseHandler": " ",
      "ticketCoCaseHandlerEmail": null,
      "ticketCoCaseHandlerPhone": null,
      "afStatus": " ",
      "ofStatus": " ",
      "invoicePeriod": null,
      "motherEventId": 70698,
      "eventAddCorr": 0,
      "eventRemark": null,
      "eventStatusReport": null,
      "ofSubmissionDate": null,
      "project": "IPA, ENI",
      "lastWorkflowStep": "Draft Event",
      "taiexContractor": "IBF - 7",
      "externalRequestId": null
    },
    {
      "eventId": 70697,
      "eventName": "DRAFT 31422 - GE - TAIEX Expert Mission on Neutral Public Internet Exchange Point (IXP) – ensuring/facilitating access to high-bandwidth and low-latency Internet within Covid-1",
      "euLegislation": "35 Other issues (Complete)",
      "city": " ",
      "startDate": 4102441200000,
      "startDateYear": 2100,
      "startDateMonth": 1,
      "endDate": 4102441200000,
      "createDate": 1594245600000,
      "ofSigned": false,
      "erSigned": " ",
      "beneficiary": "Georgia",
      "eventKeyword": "COVID 19",
      "beneficiaryInstitution": "Georgian National Communications Commission (GNCC)",
      "eventType": "ETT IND/EXP",
      "afSigned": false,
      "ibuCasehandler": " ",
      "ibuCasehandlerEmail": null,
      "ibuCasehandlerPhone": null,
      "teamLeader": "Scott BOWEN",
      "teamLeaderEmail": "Scott.BOWEN@ec.europa.eu",
      "teamLeaderPhone": "+32 229-56519",
      "coCasehandler": " ",
      "coCasehandlerEmail": null,
      "coCasehandlerPhone": null,
      "countryEventPlace": "Croatia",
      "team": "ETT",
      "eventCategory": "Expert Mission",
      "budgetGroup": "ENPI EAST",
      "taskNo": 31422,
      "eventGroup": "TAIEX strategic",
      "afSignDate": null,
      "ofSignDate": null,
      "seriesOfEvent": null,
      "accountCaseHandler": " ",
      "accountCaseHandlerEmail": null,
      "accountCaseHandlerPhone": null,
      "ticketCoCaseHandler": " ",
      "ticketCoCaseHandlerEmail": null,
      "ticketCoCaseHandlerPhone": null,
      "afStatus": " ",
      "ofStatus": " ",
      "invoicePeriod": null,
      "motherEventId": 70697,
      "eventAddCorr": 0,
      "eventRemark": null,
      "eventStatusReport": null,
      "ofSubmissionDate": null,
      "project": "IPA, ENI",
      "lastWorkflowStep": "Draft Event",
      "taiexContractor": "IBF - 7",
      "externalRequestId": null
    },
    {
      "eventId": 70696,
      "eventName": "DRAFT 31427 - AL - TAIEX Worksh",
      "euLegislation": "04 Free movement of capital [10.40] (Complete)",
      "city": "Alaverdi",
      "startDate": 4102441200000,
      "startDateYear": 2100,
      "startDateMonth": 1,
      "endDate": 4102441200000,
      "createDate": 1594245600000,
      "ofSigned": false,
      "erSigned": " ",
      "beneficiary": "Albania",
      "eventKeyword": "Crossborder payments,Crossborder payments in euros",
      "beneficiaryInstitution": "test",
      "eventType": "AGR",
      "afSigned": false,
      "ibuCasehandler": " ",
      "ibuCasehandlerEmail": null,
      "ibuCasehandlerPhone": null,
      "teamLeader": "Tatjana BORBAS",
      "teamLeaderEmail": "Tatjana.BORBAS@ec.europa.eu",
      "teamLeaderPhone": "+32 2 29 58951",
      "coCasehandler": " ",
      "coCasehandlerEmail": null,
      "coCasehandlerPhone": null,
      "countryEventPlace": "Armenia",
      "team": "AGR",
      "eventCategory": "Workshop",
      "budgetGroup": "IPA",
      "taskNo": 31427,
      "eventGroup": "TAIEX strategic",
      "afSignDate": null,
      "ofSignDate": null,
      "seriesOfEvent": null,
      "accountCaseHandler": " ",
      "accountCaseHandlerEmail": null,
      "accountCaseHandlerPhone": null,
      "ticketCoCaseHandler": " ",
      "ticketCoCaseHandlerEmail": null,
      "ticketCoCaseHandlerPhone": null,
      "afStatus": " ",
      "ofStatus": " ",
      "invoicePeriod": null,
      "motherEventId": 70696,
      "eventAddCorr": 0,
      "eventRemark": null,
      "eventStatusReport": null,
      "ofSubmissionDate": null,
      "project": "IPA, ENI",
      "lastWorkflowStep": "Draft Event",
      "taiexContractor": "IBF - 7",
      "externalRequestId": null
    },
    {
      "eventId": 70694,
      "eventName": "DRAFT 31425 - LT - TAIEX Workshop on Green procurement 31425 - LT - TAIEX Workshop on Green procurement31425 - LT - TAIEX Workshop on Green procurement31425 - LT - TAIEX Workshop on Green procurement31425 - LT - TAIEX Workshop on Green procurement31425 - LT - TAIEX Workshop on Green procurement31425 - LT - TAIEX Workshop on Green procurement31425 - LT - TAIEX Workshop on Green procurement31425",
      "euLegislation": "TO BE DEFINED",
      "city": " ",
      "startDate": 4102441200000,
      "startDateYear": 2100,
      "startDateMonth": 1,
      "endDate": 4102441200000,
      "createDate": 1594245600000,
      "ofSigned": false,
      "erSigned": " ",
      "beneficiary": "Lithuania",
      "eventKeyword": "TO BE DEFINED",
      "beneficiaryInstitution": "Ministry of Environment of the Republic of Lithuania, Environmental Projects Management Agency",
      "eventType": "REGIO",
      "afSigned": false,
      "ibuCasehandler": " ",
      "ibuCasehandlerEmail": null,
      "ibuCasehandlerPhone": null,
      "teamLeader": "Helen LARSSON",
      "teamLeaderEmail": "Helen.LARSSON@ec.europa.eu",
      "teamLeaderPhone": "+32 2 29 91978",
      "coCasehandler": " ",
      "coCasehandlerEmail": null,
      "coCasehandlerPhone": null,
      "countryEventPlace": "TO BE DEFINED",
      "team": "INT MARKT",
      "eventCategory": "Workshop",
      "budgetGroup": "REGIO",
      "taskNo": 31425,
      "eventGroup": "TAIEX strategic",
      "afSignDate": null,
      "ofSignDate": null,
      "seriesOfEvent": null,
      "accountCaseHandler": " ",
      "accountCaseHandlerEmail": null,
      "accountCaseHandlerPhone": null,
      "ticketCoCaseHandler": " ",
      "ticketCoCaseHandlerEmail": null,
      "ticketCoCaseHandlerPhone": null,
      "afStatus": " ",
      "ofStatus": " ",
      "invoicePeriod": null,
      "motherEventId": 70694,
      "eventAddCorr": 0,
      "eventRemark": null,
      "eventStatusReport": null,
      "ofSubmissionDate": null,
      "project": "REGIO PEER 2 PEER",
      "lastWorkflowStep": "Draft Event",
      "taiexContractor": "IBF - 7",
      "externalRequestId": null
    },
    {
      "eventId": 70693,
      "eventName": "DRAFT 31422 - GE - TAIEX Expert Mission on Neutral Public Internet Exchange Point (IXP) – ensuring/facilitating access to high-bandwidth and low-latency Internet within Covid-1",
      "euLegislation": "35 Other issues (Complete)",
      "city": " ",
      "startDate": 4102441200000,
      "startDateYear": 2100,
      "startDateMonth": 1,
      "endDate": 4102441200000,
      "createDate": 1594159200000,
      "ofSigned": false,
      "erSigned": " ",
      "beneficiary": "Georgia",
      "eventKeyword": "COVID 19",
      "beneficiaryInstitution": "Georgian National Communications Commission (GNCC)",
      "eventType": "ETT IND/EXP",
      "afSigned": false,
      "ibuCasehandler": " ",
      "ibuCasehandlerEmail": null,
      "ibuCasehandlerPhone": null,
      "teamLeader": "Scott BOWEN",
      "teamLeaderEmail": "Scott.BOWEN@ec.europa.eu",
      "teamLeaderPhone": "+32 229-56519",
      "coCasehandler": " ",
      "coCasehandlerEmail": null,
      "coCasehandlerPhone": null,
      "countryEventPlace": "Croatia",
      "team": "ETT",
      "eventCategory": "Expert Mission",
      "budgetGroup": "ENPI EAST",
      "taskNo": 31422,
      "eventGroup": "TAIEX standard",
      "afSignDate": null,
      "ofSignDate": null,
      "seriesOfEvent": null,
      "accountCaseHandler": " ",
      "accountCaseHandlerEmail": null,
      "accountCaseHandlerPhone": null,
      "ticketCoCaseHandler": " ",
      "ticketCoCaseHandlerEmail": null,
      "ticketCoCaseHandlerPhone": null,
      "afStatus": " ",
      "ofStatus": " ",
      "invoicePeriod": null,
      "motherEventId": 70693,
      "eventAddCorr": 0,
      "eventRemark": null,
      "eventStatusReport": null,
      "ofSubmissionDate": null,
      "project": "IPA, ENI",
      "lastWorkflowStep": "Draft Event",
      "taiexContractor": "IBF - 7",
      "externalRequestId": null
    },
    {
      "eventId": 70692,
      "eventName": "TAIEX-8 test event",
      "euLegislation": "04 Free movement of capital [10.40] (Complete)",
      "city": "Paris",
      "startDate": 1600984800000,
      "startDateYear": 2020,
      "startDateMonth": 9,
      "endDate": 1601071200000,
      "createDate": 1594072800000,
      "ofSigned": false,
      "erSigned": " ",
      "beneficiary": "TO BE DEFINED",
      "eventKeyword": "Chapter 04,COVID 19",
      "beneficiaryInstitution": null,
      "eventType": "AGR",
      "afSigned": false,
      "ibuCasehandler": "Erica ROGGIO",
      "ibuCasehandlerEmail": "Erica.ROGGIO@ec.europa.eu",
      "ibuCasehandlerPhone": "+32 2 29 66317",
      "teamLeader": "Tatjana BORBAS",
      "teamLeaderEmail": "Tatjana.BORBAS@ec.europa.eu",
      "teamLeaderPhone": "+32 2 29 58951",
      "coCasehandler": " ",
      "coCasehandlerEmail": null,
      "coCasehandlerPhone": null,
      "countryEventPlace": "France",
      "team": "AGR",
      "eventCategory": "Workshop",
      "budgetGroup": "TO BE DEFINED",
      "taskNo": null,
      "eventGroup": "TAIEX standard",
      "afSignDate": null,
      "ofSignDate": null,
      "seriesOfEvent": null,
      "accountCaseHandler": " ",
      "accountCaseHandlerEmail": null,
      "accountCaseHandlerPhone": null,
      "ticketCoCaseHandler": " ",
      "ticketCoCaseHandlerEmail": null,
      "ticketCoCaseHandlerPhone": null,
      "afStatus": " ",
      "ofStatus": " ",
      "invoicePeriod": null,
      "motherEventId": 70692,
      "eventAddCorr": 0,
      "eventRemark": null,
      "eventStatusReport": null,
      "ofSubmissionDate": null,
      "project": "IPA, ENI",
      "lastWorkflowStep": "Active event",
      "taiexContractor": "TAIEX - 8",
      "externalRequestId": null
    }
  ],
  "rowCount": 45
}
